rago/__init__.py
rago/_optional.py
rago/base.py
rago/core.py
rago/py.typed
rago/augmented/__init__.py
rago/augmented/base.py
rago/augmented/cohere.py
rago/augmented/fireworks.py
rago/augmented/openai.py
rago/augmented/sentence_transformer.py
rago/augmented/spacy.py
rago/augmented/together.py
rago/augmented/db/__init__.py
rago/augmented/db/base.py
rago/augmented/db/chroma.py
rago/augmented/db/faiss.py
rago/extensions/__init__.py
rago/extensions/base.py
rago/extensions/cache.py
rago/generation/__init__.py
rago/generation/base.py
rago/generation/cohere.py
rago/generation/deepseek.py
rago/generation/fireworks.py
rago/generation/gemini.py
rago/generation/groq.py
rago/generation/hugging_face.py
rago/generation/hugging_face_inf.py
rago/generation/llama.py
rago/generation/openai.py
rago/generation/phi.py
rago/generation/together.py
rago/retrieval/__init__.py
rago/retrieval/base.py
rago/retrieval/dummy.py
rago/retrieval/file.py
rago/retrieval/text_splitter/__init__.py
rago/retrieval/text_splitter/base.py
rago/retrieval/text_splitter/langchain.py
rago/retrieval/tools/__init__.py
rago/retrieval/tools/pdf.py
rago-0.14.4.dist-info/licenses/LICENSE
rago-0.14.4.dist-info/METADATA
rago-0.14.4.dist-info/WHEEL
rago-0.14.4.dist-info/top_level.txt
rago-0.14.4.dist-info/RECORD
