Metadata-Version: 2.4
Name: rago
Version: 0.14.4
Summary: RAG framework
Author-email: Ivan Ogasawara <ivan.ogasawara@gmail.com>
License: MIT
Project-URL: Homepage, https://github.com/osl-incubator/rago
Project-URL: Issues, https://github.com/osl-incubator/rago/issues
Requires-Python: <4,>=3.9
License-File: LICENSE
Requires-Dist: typeguard>=4.0
Requires-Dist: pydantic>=2
Requires-Dist: joblib>=1.4.2
Requires-Dist: pypdf>=5
Requires-Dist: torch>=2
Requires-Dist: langchain>=0.3.7
Requires-Dist: langchain-community>=0.3.7
Requires-Dist: instructor>=1
Requires-Dist: openai>=1.52.2
Requires-Dist: numpy<2,>=1.26; python_version < "3.13" and sys_platform == "darwin"
Requires-Dist: numpy>=2; python_version >= "3.13" and sys_platform == "darwin"
Requires-Dist: numpy<2.1,>=2; python_version < "3.10" and sys_platform != "darwin"
Requires-Dist: numpy<2.2,>=2; python_version == "3.10" and sys_platform != "darwin"
Requires-Dist: numpy>=2; python_version >= "3.11" and sys_platform != "darwin"
Requires-Dist: faiss-cpu<1.9,>=1.8.0; sys_platform == "darwin" and python_version < "3.13"
Requires-Dist: faiss-cpu>=1.9.0; sys_platform != "darwin" or python_version >= "3.13"
Requires-Dist: typing-extensions>=4.8; python_version < "3.11"
Provides-Extra: chromadb
Requires-Dist: chromadb>=0.3.23; extra == "chromadb"
Provides-Extra: google
Requires-Dist: google-generativeai>=0.8.3; extra == "google"
Provides-Extra: cohere
Requires-Dist: cohere>=5.13.4; extra == "cohere"
Provides-Extra: fireworks
Requires-Dist: fireworks-ai<1.0.0,>=0.15.11; extra == "fireworks"
Provides-Extra: together
Requires-Dist: together>=1.4.0; extra == "together"
Provides-Extra: ollama
Requires-Dist: ollama>=0.4.8; extra == "ollama"
Provides-Extra: base
Requires-Dist: transformers>=4; extra == "base"
Requires-Dist: sentence-transformers>=3.2.0; extra == "base"
Requires-Dist: sentencepiece>=0.2.0; extra == "base"
Requires-Dist: langdetect>=1; extra == "base"
Provides-Extra: all
Requires-Dist: google-generativeai>=0.8.3; extra == "all"
Requires-Dist: cohere>=5.13.4; extra == "all"
Requires-Dist: fireworks-ai<1.0.0,>=0.15.11; extra == "all"
Requires-Dist: together>=1.4.0; extra == "all"
Requires-Dist: ollama>=0.4.8; extra == "all"
Requires-Dist: spacy>=3.8.0; extra == "all"
Requires-Dist: chromadb>=0.3.23; extra == "all"
Requires-Dist: transformers>=4; extra == "all"
Requires-Dist: sentence-transformers>=3.2.0; extra == "all"
Requires-Dist: sentencepiece>=0.2.0; extra == "all"
Requires-Dist: langdetect>=1; extra == "all"
Provides-Extra: dev
Requires-Dist: pytest>=6; extra == "dev"
Requires-Dist: pytest-cov>=6.2; extra == "dev"
Requires-Dist: coverage>=7.10; extra == "dev"
Requires-Dist: pre-commit>=4.3; extra == "dev"
Requires-Dist: ruff>=0.12.0; extra == "dev"
Requires-Dist: mypy>=1.17.0; extra == "dev"
Requires-Dist: bandit>=1.8; extra == "dev"
Requires-Dist: vulture>=2.14; extra == "dev"
Requires-Dist: mccabe>=0.7; extra == "dev"
Requires-Dist: ipython>=6; extra == "dev"
Requires-Dist: ipykernel>=5; extra == "dev"
Requires-Dist: python-dotenv>=1.1; extra == "dev"
Requires-Dist: Jinja2>=3.1.2; extra == "dev"
Requires-Dist: makim==1.27.0; extra == "dev"
Requires-Dist: mkdocs>=1.6; extra == "dev"
Requires-Dist: mkdocs-exclude>=1.0.2; extra == "dev"
Requires-Dist: mkdocs-jupyter>=0.25; extra == "dev"
Requires-Dist: mkdocs-literate-nav>=0.6; extra == "dev"
Requires-Dist: mkdocs-macros-plugin>=1.3; extra == "dev"
Requires-Dist: mkdocs-material>=9.6; extra == "dev"
Requires-Dist: mkdocstrings>=0.30; extra == "dev"
Requires-Dist: mkdocstrings-python>=1.17; extra == "dev"
Requires-Dist: mkdocs-gen-files>=0.5.0; extra == "dev"
Requires-Dist: build>=1.3.0; extra == "dev"
Requires-Dist: twine>=6.1.0; extra == "dev"
Dynamic: license-file
